[
    {
      "classId": "X050SC1",
      "className": "301 Science",
      "totalStudents": 16,
      "classLink": "https://www.classswift.viewsonic.io/",
      "qrCode": ""
    },
    {
      "classId": "X050SC2",
      "className": "302 Science",
      "totalStudents": 16,
      "classLink": "https://www.classswift.viewsonic.io/",
      "qrCode": ""
    },
    {
      "classId": "X050SC3",
      "className": "303 Science",
      "totalStudents": 16,
      "classLink": "https://www.classswift.viewsonic.io/",
      "qrCode": ""
    }
  ]